{"context":{"earlier":"3|OB|MT#14#451589#451589#451877#451877#0#0#485#451576#1#0#27#0#0#-2147483648#1#2|PDH#bbe10b32f5270e429a5a473728022d1b|RD#18102023|RT#141653|US#0|RS#INIT","later":"3|OF|MT#14#451774#451774#452001#452001#0#0#485#451710#6#0#27#0#0#-2147483648#1#2|PDH#bbe10b32f5270e429a5a473728022d1b|RD#18102023|RT#141653|US#0|RS#INIT"},"routes":[{"checksum":"6859cf97_3","cid":"C-0","date":"2023-10-17T22:00:00.000Z","duration":17280000,"changes":1,"isRideable":true,"arrival":{"platform":"8","scheduledTime":"2023-10-18T17:17:00.000Z","time":"2023-10-18T17:17:00.000Z","reihung":false},"departure":{"platform":"2","scheduledTime":"2023-10-18T12:29:00.000Z","time":"2023-10-18T12:29:00.000Z","reihung":false},"segments":[{"arrival":{"platform":"8","scheduledTime":"2023-10-18T15:53:00.000Z","time":"2023-10-18T15:53:00.000Z","reihung":false},"departure":{"platform":"2","scheduledTime":"2023-10-18T12:29:00.000Z","time":"2023-10-18T12:29:00.000Z","reihung":false},"duration":12240000,"wings":[{"train":{"name":"ICE 1711","line":"28","admin":"80","number":"1711","type":"ICE","operator":{"name":"DB Fernverkehr AG","icoX":1}},"segmentStart":{"name":"Berlin Hbf (tief)","evaNumber":"8098160"},"segmentDestination":{"name":"Nürnberg Hbf","evaNumber":"8000284"},"stops":[{"station":{"evaNumber":"8098160","name":"Berlin Hbf (tief)","coordinates":{"lng":13.368892,"lat":52.52585},"ril100":"BL"},"departure":{"platform":"2","scheduledTime":"2023-10-18T12:29:00.000Z","time":"2023-10-18T12:29:00.000Z","reihung":false}},{"station":{"evaNumber":"8011113","name":"Berlin Südkreuz","coordinates":{"lng":13.365863,"lat":52.47623},"ril100":"BPAF"},"arrival":{"platform":"5","scheduledTime":"2023-10-18T12:34:00.000Z","time":"2023-10-18T12:34:00.000Z","reihung":false},"auslastung":{"first":2,"second":2}},{"station":{"evaNumber":"8010222","name":"Lutherstadt Wittenberg Hbf","coordinates":{"lng":12.661999,"lat":51.867579},"ril100":"LW"},"arrival":{"platform":"2","scheduledTime":"2023-10-18T13:10:00.000Z","time":"2023-10-18T13:10:00.000Z","reihung":false},"auslastung":{"first":3,"second":2}},{"station":{"evaNumber":"8010205","name":"Leipzig Hbf","coordinates":{"lng":12.381167,"lat":51.345081},"ril100":"LL"},"arrival":{"platform":"13","scheduledTime":"2023-10-18T13:42:00.000Z","time":"2023-10-18T13:42:00.000Z","reihung":false},"auslastung":{"first":3,"second":2}},{"station":{"evaNumber":"8010101","name":"Erfurt Hbf","coordinates":{"lng":11.038502,"lat":50.97255},"ril100":"UE  P"},"arrival":{"platform":"1","scheduledTime":"2023-10-18T14:29:00.000Z","time":"2023-10-18T14:29:00.000Z","reihung":false},"auslastung":{"first":3,"second":2}},{"station":{"evaNumber":"8001844","name":"Erlangen","coordinates":{"lng":11.001664,"lat":49.595969},"ril100":"NER"},"arrival":{"platform":"4","scheduledTime":"2023-10-18T15:36:00.000Z","time":"2023-10-18T15:36:00.000Z","reihung":false},"auslastung":{"first":2,"second":1}},{"station":{"evaNumber":"8000284","name":"Nürnberg Hbf","coordinates":{"lng":11.08227,"lat":49.445435},"ril100":"NN"},"arrival":{"platform":"8","scheduledTime":"2023-10-18T15:53:00.000Z","time":"2023-10-18T15:53:00.000Z","reihung":false}}],"finalDestination":"München Hbf","jid":"1|199289|0|80|18102023","auslastung":{"first":3,"second":2}}],"train":{"name":"ICE 1601","line":"28","admin":"80","number":"1601","type":"ICE","operator":{"name":"DB Fernverkehr AG","icoX":1}},"changeDuration":12,"segmentStart":{"name":"Berlin Hbf (tief)","evaNumber":"8098160"},"segmentDestination":{"name":"Nürnberg Hbf","evaNumber":"8000284"},"stops":[{"station":{"evaNumber":"8098160","name":"Berlin Hbf (tief)","coordinates":{"lng":13.368892,"lat":52.52585},"ril100":"BL"},"departure":{"platform":"2","scheduledTime":"2023-10-18T12:29:00.000Z","time":"2023-10-18T12:29:00.000Z","reihung":false}},{"station":{"evaNumber":"8011113","name":"Berlin Südkreuz","coordinates":{"lng":13.365863,"lat":52.47623},"ril100":"BPAF"},"arrival":{"platform":"5","scheduledTime":"2023-10-18T12:34:00.000Z","time":"2023-10-18T12:34:00.000Z","reihung":false},"departure":{"platform":"5","scheduledTime":"2023-10-18T12:36:00.000Z","time":"2023-10-18T12:36:00.000Z","reihung":false},"auslastung":{"first":2,"second":2}},{"station":{"evaNumber":"8010222","name":"Lutherstadt Wittenberg Hbf","coordinates":{"lng":12.661999,"lat":51.867579},"ril100":"LW"},"arrival":{"platform":"2","scheduledTime":"2023-10-18T13:10:00.000Z","time":"2023-10-18T13:10:00.000Z","reihung":false},"departure":{"platform":"2","scheduledTime":"2023-10-18T13:11:00.000Z","time":"2023-10-18T13:11:00.000Z","reihung":false},"auslastung":{"first":3,"second":2}},{"station":{"evaNumber":"8010205","name":"Leipzig Hbf","coordinates":{"lng":12.381167,"lat":51.345081},"ril100":"LL"},"arrival":{"platform":"13","scheduledTime":"2023-10-18T13:42:00.000Z","time":"2023-10-18T13:42:00.000Z","reihung":false},"departure":{"platform":"13","scheduledTime":"2023-10-18T13:48:00.000Z","time":"2023-10-18T13:48:00.000Z","reihung":false},"auslastung":{"first":3,"second":2}},{"station":{"evaNumber":"8010101","name":"Erfurt Hbf","coordinates":{"lng":11.038502,"lat":50.97255},"ril100":"UE  P"},"arrival":{"platform":"1","scheduledTime":"2023-10-18T14:29:00.000Z","time":"2023-10-18T14:29:00.000Z","reihung":false},"departure":{"platform":"1","scheduledTime":"2023-10-18T14:31:00.000Z","time":"2023-10-18T14:31:00.000Z","reihung":false},"auslastung":{"first":3,"second":2}},{"station":{"evaNumber":"8001844","name":"Erlangen","coordinates":{"lng":11.001664,"lat":49.595969},"ril100":"NER"},"arrival":{"platform":"4","scheduledTime":"2023-10-18T15:36:00.000Z","time":"2023-10-18T15:36:00.000Z","reihung":false},"departure":{"platform":"4","scheduledTime":"2023-10-18T15:38:00.000Z","time":"2023-10-18T15:38:00.000Z","reihung":false},"auslastung":{"first":2,"second":1}},{"station":{"evaNumber":"8000284","name":"Nürnberg Hbf","coordinates":{"lng":11.08227,"lat":49.445435},"ril100":"NN"},"arrival":{"platform":"8","scheduledTime":"2023-10-18T15:53:00.000Z","time":"2023-10-18T15:53:00.000Z","reihung":false}}],"finalDestination":"München Hbf","jid":"1|198466|0|80|18102023","auslastung":{"first":3,"second":2},"messages":[{"type":"A","code":"CK","prio":200,"icoX":2,"txtN":"Sicher & kontaktlos ohne Ticketkontrolle reisen mit Komfort Check-in"},{"type":"A","code":"FR","prio":260,"icoX":3,"txtN":"Fahrradmitnahme reservierungspflichtig"},{"type":"A","code":"FB","prio":260,"icoX":4,"txtN":"Fahrradmitnahme begrenzt möglich"},{"type":"A","code":"BR","prio":450,"icoX":5,"txtN":"Bordrestaurant"}],"type":"JNY"},{"arrival":{"platform":"8","scheduledTime":"2023-10-18T17:17:00.000Z","time":"2023-10-18T17:17:00.000Z","reihung":false},"departure":{"platform":"19","scheduledTime":"2023-10-18T16:05:00.000Z","time":"2023-10-18T16:05:00.000Z","reihung":false},"duration":4320000,"train":{"name":"RE 10","line":"10","admin":"800714","number":"58228","type":"RE","operator":{"name":"DB Regio AG Bayern","icoX":7}},"segmentStart":{"name":"Nürnberg Hbf","evaNumber":"8000284"},"segmentDestination":{"name":"Würzburg Hbf","evaNumber":"8000260"},"stops":[{"station":{"evaNumber":"8000284","name":"Nürnberg Hbf","coordinates":{"lng":11.08227,"lat":49.445435},"ril100":"NN"},"departure":{"platform":"19","scheduledTime":"2023-10-18T16:05:00.000Z","time":"2023-10-18T16:05:00.000Z","reihung":false}},{"station":{"evaNumber":"8000114","name":"Fürth(Bay)Hbf","coordinates":{"lng":10.989987,"lat":49.469724},"ril100":"NF"},"arrival":{"platform":"4","scheduledTime":"2023-10-18T16:10:00.000Z","time":"2023-10-18T16:10:00.000Z","reihung":false},"departure":{"platform":"4","scheduledTime":"2023-10-18T16:11:00.000Z","time":"2023-10-18T16:11:00.000Z","reihung":false}},{"station":{"evaNumber":"8005557","name":"Siegelsdorf","coordinates":{"lng":10.875914,"lat":49.506328},"ril100":"NSDF"},"arrival":{"platform":"1","scheduledTime":"2023-10-18T16:16:00.000Z","time":"2023-10-18T16:16:00.000Z","reihung":false},"departure":{"platform":"1","scheduledTime":"2023-10-18T16:17:00.000Z","time":"2023-10-18T16:17:00.000Z","reihung":false}},{"station":{"evaNumber":"8001783","name":"Emskirchen","coordinates":{"lng":10.70991,"lat":49.555041},"ril100":"NEK"},"arrival":{"platform":"2","scheduledTime":"2023-10-18T16:26:00.000Z","time":"2023-10-18T16:26:00.000Z","reihung":false},"departure":{"platform":"2","scheduledTime":"2023-10-18T16:26:00.000Z","time":"2023-10-18T16:26:00.000Z","reihung":false}},{"station":{"evaNumber":"8004323","name":"Neustadt(Aisch)Bahnhof","coordinates":{"lng":10.588178,"lat":49.576795},"ril100":"NNA"},"arrival":{"platform":"2","scheduledTime":"2023-10-18T16:33:00.000Z","time":"2023-10-18T16:33:00.000Z","reihung":false},"departure":{"platform":"2","scheduledTime":"2023-10-18T16:34:00.000Z","time":"2023-10-18T16:34:00.000Z","reihung":false}},{"station":{"evaNumber":"8003876","name":"Markt Bibart","coordinates":{"lng":10.425473,"lat":49.646084},"ril100":"NMB"},"arrival":{"platform":"1","scheduledTime":"2023-10-18T16:42:00.000Z","time":"2023-10-18T16:42:00.000Z","reihung":false},"departure":{"platform":"1","scheduledTime":"2023-10-18T16:42:00.000Z","time":"2023-10-18T16:42:00.000Z","reihung":false}},{"station":{"evaNumber":"8003081","name":"Iphofen","coordinates":{"lng":10.255047,"lat":49.696846},"ril100":"NI"},"arrival":{"platform":"2","scheduledTime":"2023-10-18T16:50:00.000Z","time":"2023-10-18T16:50:00.000Z","reihung":false},"departure":{"platform":"2","scheduledTime":"2023-10-18T16:51:00.000Z","time":"2023-10-18T16:51:00.000Z","reihung":false}},{"station":{"evaNumber":"8000479","name":"Kitzingen","coordinates":{"lng":10.155294,"lat":49.732506},"ril100":"NKN"},"arrival":{"platform":"2","scheduledTime":"2023-10-18T16:56:00.000Z","time":"2023-10-18T16:56:00.000Z","reihung":false},"departure":{"platform":"2","scheduledTime":"2023-10-18T16:57:00.000Z","time":"2023-10-18T16:57:00.000Z","reihung":false}},{"station":{"evaNumber":"8001225","name":"Buchbrunn-Mainstockheim","coordinates":{"lng":10.145423,"lat":49.762917},"ril100":"NBM"},"arrival":{"platform":"1","scheduledTime":"2023-10-18T17:00:00.000Z","time":"2023-10-18T17:00:00.000Z","reihung":false},"departure":{"platform":"1","scheduledTime":"2023-10-18T17:00:00.000Z","time":"2023-10-18T17:00:00.000Z","reihung":false}},{"station":{"evaNumber":"8001421","name":"Dettelbach Bahnhof","coordinates":{"lng":10.089196,"lat":49.789111},"ril100":"NDEB"},"arrival":{"platform":"1","scheduledTime":"2023-10-18T17:04:00.000Z","time":"2023-10-18T17:04:00.000Z","reihung":false},"departure":{"platform":"1","scheduledTime":"2023-10-18T17:04:00.000Z","time":"2023-10-18T17:04:00.000Z","reihung":false}},{"station":{"evaNumber":"8005198","name":"Rottendorf","coordinates":{"lng":10.029148,"lat":49.792024},"ril100":"NRTD"},"arrival":{"platform":"5","scheduledTime":"2023-10-18T17:08:00.000Z","time":"2023-10-18T17:08:00.000Z","reihung":false},"departure":{"platform":"5","scheduledTime":"2023-10-18T17:09:00.000Z","time":"2023-10-18T17:09:00.000Z","reihung":false}},{"station":{"evaNumber":"8000260","name":"Würzburg Hbf","coordinates":{"lng":9.93593,"lat":49.802163},"ril100":"NWH"},"arrival":{"platform":"8","scheduledTime":"2023-10-18T17:17:00.000Z","time":"2023-10-18T17:17:00.000Z","reihung":false}}],"finalDestination":"Würzburg Hbf","jid":"1|269571|1|80|18102023","messages":[{"type":"A","code":"FB","prio":260,"icoX":4,"txtN":"Fahrradmitnahme begrenzt möglich"},{"type":"A","code":"EH","prio":560,"icoX":2,"txtN":"Fahrzeuggebundene Einstiegshilfe vorhanden"},{"type":"A","code":"KL","prio":610,"icoX":2,"txtN":"Klimaanlage"},{"type":"M","code":"","icoX":10,"txtS":"RE 58228: Nürnberg Hbf->Würzburg Hbf: Bauarbeiten.","txtN":"Bauarbeiten zwischen Bamberg und Nürnberg Hbf in der Zeit vom 10. Dezember bis 16. Dezember 2023. Es kommt zu Fahrplanänderungen und Zugausfällen mit Schienenersatzverkehr. Wichtige Informationen finden Sie unter: https://t1p.de/px28w","url":"https://t1p.de/ftht0","sIdx":1}],"type":"JNY"}],"segmentTypes":["ICE","RE"]},{"checksum":"bfdf26a7_3","cid":"C-1","date":"2023-10-17T22:00:00.000Z","duration":16080000,"changes":1,"isRideable":true,"arrival":{"platform":"7","scheduledTime":"2023-10-18T17:55:00.000Z","time":"2023-10-18T17:55:00.000Z","reihung":false},"departure":{"platform":"4","scheduledTime":"2023-10-18T13:27:00.000Z","time":"2023-10-18T13:27:00.000Z","reihung":false},"segments":[{"arrival":{"platform":"1","scheduledTime":"2023-10-18T15:18:00.000Z","time":"2023-10-18T15:18:00.000Z","reihung":false},"departure":{"platform":"4","scheduledTime":"2023-10-18T13:27:00.000Z","time":"2023-10-18T13:27:00.000Z","reihung":false},"duration":6660000,"train":{"name":"FLX 1247","line":"10","admin":"FLX10","number":"1247","type":"FLX","operator":{"name":"FlixTrain","icoX":12}},"changeDuration":17,"segmentStart":{"name":"Berlin Hbf (tief)","evaNumber":"8098160"},"segmentDestination":{"name":"Erfurt Hbf","evaNumber":"8010101"},"stops":[{"station":{"evaNumber":"8098160","name":"Berlin Hbf (tief)","coordinates":{"lng":13.368892,"lat":52.52585},"ril100":"BL"},"departure":{"platform":"4","scheduledTime":"2023-10-18T13:27:00.000Z","time":"2023-10-18T13:27:00.000Z","reihung":false}},{"station":{"evaNumber":"8010159","name":"Halle(Saale)Hbf","coordinates":{"lng":11.98699,"lat":51.477079},"ril100":"LH"},"arrival":{"platform":"6","scheduledTime":"2023-10-18T14:42:00.000Z","time":"2023-10-18T14:42:00.000Z","reihung":false},"departure":{"platform":"6","scheduledTime":"2023-10-18T14:44:00.000Z","time":"2023-10-18T14:44:00.000Z","reihung":false}},{"station":{"evaNumber":"8010101","name":"Erfurt Hbf","coordinates":{"lng":11.038502,"lat":50.97255},"ril100":"UE  P"},"arrival":{"platform":"1","scheduledTime":"2023-10-18T15:18:00.000Z","time":"2023-10-18T15:18:00.000Z","reihung":false}}],"finalDestination":"Stuttgart Hbf","jid":"1|286358|0|80|18102023","messages":[{"type":"A","code":"DU","prio":110,"icoX":2,"txtN":"DB-Fahrscheine gelten nicht"},{"type":"A","code":"RP","prio":185,"icoX":13,"txtN":"Reservierungspflicht"},{"type":"A","code":"9N","prio":186,"icoX":2,"txtN":"Deutschland-Ticket nicht gültig"},{"type":"A","code":"FN","prio":555,"icoX":2,"txtN":"Einstieg nur mit gültigem FlixTrain- oder FlixBus Ticket"},{"type":"A","code":"FX","prio":560,"icoX":2,"txtN":"Tickets unter www.flixtrain.de"},{"type":"A","code":"FG","prio":603,"icoX":2,"txtN":"Sitzplatzgarantie"},{"type":"A","code":"LS","prio":605,"icoX":2,"txtN":"Laptop-Steckdosen"},{"type":"A","code":"WV","prio":710,"icoX":2,"txtN":"WLAN verfügbar"}],"type":"JNY"},{"arrival":{"platform":"7","scheduledTime":"2023-10-18T17:55:00.000Z","time":"2023-10-18T17:55:00.000Z","reihung":false},"departure":{"platform":"3a","scheduledTime":"2023-10-18T15:35:00.000Z","time":"2023-10-18T15:35:00.000Z","reihung":false},"duration":8400000,"train":{"name":"RE 7","line":"7","admin":"8004NT","number":"3765","type":"RE","operator":{"name":"DB Regio AG Südost","icoX":14}},"segmentStart":{"name":"Erfurt Hbf","evaNumber":"8010101"},"segmentDestination":{"name":"Würzburg Hbf","evaNumber":"8000260"},"stops":[{"station":{"evaNumber":"8010101","name":"Erfurt Hbf","coordinates":{"lng":11.038502,"lat":50.97255},"ril100":"UE  P"},"departure":{"platform":"3a","scheduledTime":"2023-10-18T15:35:00.000Z","time":"2023-10-18T15:35:00.000Z","reihung":false}},{"station":{"evaNumber":"8010242","name":"Neudietendorf","coordinates":{"lng":10.910477,"lat":50.914246},"ril100":"UND"},"arrival":{"platform":"2","scheduledTime":"2023-10-18T15:43:00.000Z","time":"2023-10-18T15:43:00.000Z","reihung":false},"departure":{"platform":"2","scheduledTime":"2023-10-18T15:43:00.000Z","time":"2023-10-18T15:43:00.000Z","reihung":false}},{"station":{"evaNumber":"8010007","name":"Arnstadt Hbf","coordinates":{"lng":10.948259,"lat":50.842063},"ril100":"UA"},"arrival":{"platform":"3","scheduledTime":"2023-10-18T15:50:00.000Z","time":"2023-10-18T15:50:00.000Z","reihung":false},"departure":{"platform":"3","scheduledTime":"2023-10-18T15:51:00.000Z","time":"2023-10-18T15:51:00.000Z","reihung":false}},{"station":{"evaNumber":"8010274","name":"Plaue(Thür)","coordinates":{"lng":10.908725,"lat":50.778356},"ril100":"UPL"},"arrival":{"platform":"1","scheduledTime":"2023-10-18T15:57:00.000Z","time":"2023-10-18T15:57:00.000Z","reihung":false},"departure":{"platform":"1","scheduledTime":"2023-10-18T15:58:00.000Z","time":"2023-10-18T15:58:00.000Z","reihung":false}},{"station":{"evaNumber":"8010391","name":"Zella-Mehlis","coordinates":{"lng":10.674106,"lat":50.646655},"ril100":"UZL"},"arrival":{"platform":"3","scheduledTime":"2023-10-18T16:16:00.000Z","time":"2023-10-18T16:16:00.000Z","reihung":false},"departure":{"platform":"3","scheduledTime":"2023-10-18T16:16:00.000Z","time":"2023-10-18T16:16:00.000Z","reihung":false}},{"station":{"evaNumber":"8010345","name":"Suhl","coordinates":{"lng":10.68288,"lat":50.605242},"ril100":"USL"},"arrival":{"platform":"1","scheduledTime":"2023-10-18T16:21:00.000Z","time":"2023-10-18T16:21:00.000Z","reihung":false},"departure":{"platform":"1","scheduledTime":"2023-10-18T16:22:00.000Z","time":"2023-10-18T16:22:00.000Z","reihung":false}},{"station":{"evaNumber":"8010142","name":"Grimmenthal","coordinates":{"lng":10.450616,"lat":50.532825},"ril100":"UGM"},"arrival":{"platform":"3","scheduledTime":"2023-10-18T16:32:00.000Z","time":"2023-10-18T16:32:00.000Z","reihung":false},"departure":{"platform":"3","scheduledTime":"2023-10-18T16:35:00.000Z","time":"2023-10-18T16:35:00.000Z","reihung":false}},{"station":{"evaNumber":"8003959","name":"Mellrichstadt Bf","coordinates":{"lng":10.306717,"lat":50.42446},"ril100":"NME"},"arrival":{"platform":"3","scheduledTime":"2023-10-18T16:48:00.000Z","time":"2023-10-18T16:48:00.000Z","reihung":false},"departure":{"platform":"3","scheduledTime":"2023-10-18T16:49:00.000Z","time":"2023-10-18T16:49:00.000Z","reihung":false}},{"station":{"evaNumber":"8000730","name":"Bad Neustadt(Saale)","coordinates":{"lng":10.226246,"lat":50.328293},"ril100":"NBNE"},"arrival":{"platform":"3","scheduledTime":"2023-10-18T16:56:00.000Z","time":"2023-10-18T16:56:00.000Z","reihung":false},"departure":{"platform":"3","scheduledTime":"2023-10-18T16:57:00.000Z","time":"2023-10-18T16:57:00.000Z","reihung":false}},{"station":{"evaNumber":"8004169","name":"Münnerstadt","coordinates":{"lng":10.188743,"lat":50.250015},"ril100":"NMUE"},"arrival":{"platform":"1","scheduledTime":"2023-10-18T17:03:00.000Z","time":"2023-10-18T17:03:00.000Z","reihung":false},"departure":{"platform":"1","scheduledTime":"2023-10-18T17:03:00.000Z","time":"2023-10-18T17:03:00.000Z","reihung":false}},{"station":{"evaNumber":"8001620","name":"Ebenhausen(Unterfr)","coordinates":{"lng":10.138088,"lat":50.13107},"ril100":"NEBH"},"arrival":{"platform":"3","scheduledTime":"2023-10-18T17:12:00.000Z","time":"2023-10-18T17:12:00.000Z","reihung":false},"departure":{"platform":"3","scheduledTime":"2023-10-18T17:17:00.000Z","time":"2023-10-18T17:17:00.000Z","reihung":false}},{"station":{"evaNumber":"8000032","name":"Schweinfurt Hbf","coordinates":{"lng":10.211899,"lat":50.035101},"ril100":"NS"},"arrival":{"platform":"6","scheduledTime":"2023-10-18T17:26:00.000Z","time":"2023-10-18T17:26:00.000Z","reihung":false},"departure":{"platform":"6","scheduledTime":"2023-10-18T17:32:00.000Z","time":"2023-10-18T17:32:00.000Z","reihung":false}},{"station":{"evaNumber":"8000260","name":"Würzburg Hbf","coordinates":{"lng":9.93593,"lat":49.802163},"ril100":"NWH"},"arrival":{"platform":"7","scheduledTime":"2023-10-18T17:55:00.000Z","time":"2023-10-18T17:55:00.000Z","reihung":false}}],"finalDestination":"Würzburg Hbf","jid":"1|246918|0|80|18102023","messages":[{"type":"A","code":"FB","prio":260,"icoX":4,"txtN":"Fahrradmitnahme begrenzt möglich"}],"type":"JNY"}],"segmentTypes":["FLX","RE"]},{"checksum":"5d1b7d82_3","cid":"C-2","date":"2023-10-17T22:00:00.000Z","duration":13620000,"changes":1,"isRideable":true,"arrival":{"platform":"10 D-F","scheduledTime":"2023-10-18T17:21:00.000Z","time":"2023-10-18T17:21:00.000Z","reihung":false},"departure":{"platform":"1","scheduledTime":"2023-10-18T13:34:00.000Z","time":"2023-10-18T13:34:00.000Z","reihung":false},"segments":[{"arrival":{"platform":"3","scheduledTime":"2023-10-18T16:15:00.000Z","time":"2023-10-18T16:15:00.000Z","reihung":false},"departure":{"platform":"1","scheduledTime":"2023-10-18T13:34:00.000Z","time":"2023-10-18T13:34:00.000Z","reihung":false},"duration":9660000,"train":{"name":"ICE 709","line":"18","admin":"80","number":"709","type":"ICE","operator":{"name":"DB Fernverkehr AG","icoX":1}},"changeDuration":12,"segmentStart":{"name":"Berlin Hbf (tief)","evaNumber":"8098160"},"segmentDestination":{"name":"Bamberg","evaNumber":"8000025"},"stops":[{"station":{"evaNumber":"8098160","name":"Berlin Hbf (tief)","coordinates":{"lng":13.368892,"lat":52.52585},"ril100":"BL"},"departure":{"platform":"1","scheduledTime":"2023-10-18T13:34:00.000Z","time":"2023-10-18T13:34:00.000Z","reihung":false}},{"station":{"evaNumber":"8011113","name":"Berlin Südkreuz","coordinates":{"lng":13.365863,"lat":52.47623},"ril100":"BPAF"},"arrival":{"platform":"3","scheduledTime":"2023-10-18T13:39:00.000Z","time":"2023-10-18T13:39:00.000Z","reihung":false},"departure":{"platform":"3","scheduledTime":"2023-10-18T13:41:00.000Z","time":"2023-10-18T13:41:00.000Z","reihung":false},"auslastung":{"first":1,"second":1}},{"station":{"evaNumber":"8010050","name":"Bitterfeld","coordinates":{"lng":12.316966,"lat":51.622911},"ril100":"LBT"},"arrival":{"platform":"3","scheduledTime":"2023-10-18T14:32:00.000Z","time":"2023-10-18T14:32:00.000Z","reihung":false},"departure":{"platform":"3","scheduledTime":"2023-10-18T14:33:00.000Z","time":"2023-10-18T14:33:00.000Z","reihung":false},"auslastung":{"first":1,"second":1}},{"station":{"evaNumber":"8010159","name":"Halle(Saale)Hbf","coordinates":{"lng":11.98699,"lat":51.477079},"ril100":"LH"},"arrival":{"platform":"8","scheduledTime":"2023-10-18T14:51:00.000Z","time":"2023-10-18T14:51:00.000Z","reihung":false},"departure":{"platform":"8","scheduledTime":"2023-10-18T14:53:00.000Z","time":"2023-10-18T14:53:00.000Z","reihung":false},"auslastung":{"first":1,"second":1}},{"station":{"evaNumber":"8010101","name":"Erfurt Hbf","coordinates":{"lng":11.038502,"lat":50.97255},"ril100":"UE  P"},"arrival":{"platform":"1","scheduledTime":"2023-10-18T15:24:00.000Z","time":"2023-10-18T15:24:00.000Z","reihung":false},"departure":{"platform":"1","scheduledTime":"2023-10-18T15:32:00.000Z","time":"2023-10-18T15:32:00.000Z","reihung":false},"auslastung":{"first":1,"second":1}},{"station":{"evaNumber":"8000025","name":"Bamberg","coordinates":{"lng":10.899493,"lat":49.900793},"ril100":"NBA"},"arrival":{"platform":"3","scheduledTime":"2023-10-18T16:15:00.000Z","time":"2023-10-18T16:15:00.000Z","reihung":false}}],"finalDestination":"München Hbf","jid":"1|209234|0|80|18102023","auslastung":{"first":1,"second":1},"messages":[{"type":"A","code":"CK","prio":200,"icoX":2,"txtN":"Sicher & kontaktlos ohne Ticketkontrolle reisen mit Komfort Check-in"},{"type":"A","code":"FR","prio":260,"icoX":3,"txtN":"Fahrradmitnahme reservierungspflichtig"},{"type":"A","code":"FB","prio":260,"icoX":4,"txtN":"Fahrradmitnahme begrenzt möglich"},{"type":"A","code":"BR","prio":450,"icoX":5,"txtN":"Bordrestaurant"},{"type":"A","code":"EH","prio":560,"icoX":2,"txtN":"Fahrzeuggebundene Einstiegshilfe vorhanden"}],"type":"JNY"},{"arrival":{"platform":"10 D-F","scheduledTime":"2023-10-18T17:21:00.000Z","time":"2023-10-18T17:21:00.000Z","reihung":false},"departure":{"platform":"6","scheduledTime":"2023-10-18T16:27:00.000Z","time":"2023-10-18T16:27:00.000Z","reihung":false},"duration":3240000,"train":{"name":"RE 20","line":"20","admin":"800755","number":"4794","type":"RE","operator":{"name":"DB Regio AG Bayern","icoX":7}},"segmentStart":{"name":"Bamberg","evaNumber":"8000025"},"segmentDestination":{"name":"Würzburg Hbf","evaNumber":"8000260"},"stops":[{"station":{"evaNumber":"8000025","name":"Bamberg","coordinates":{"lng":10.899493,"lat":49.900793},"ril100":"NBA"},"departure":{"platform":"6","scheduledTime":"2023-10-18T16:27:00.000Z","time":"2023-10-18T16:27:00.000Z","reihung":false}},{"station":{"evaNumber":"8002630","name":"Haßfurt","coordinates":{"lng":10.509765,"lat":50.033366},"ril100":"NHT"},"arrival":{"platform":"2","scheduledTime":"2023-10-18T16:43:00.000Z","time":"2023-10-18T16:43:00.000Z","reihung":false},"departure":{"platform":"2","scheduledTime":"2023-10-18T16:43:00.000Z","time":"2023-10-18T16:43:00.000Z","reihung":false}},{"station":{"evaNumber":"8000032","name":"Schweinfurt Hbf","coordinates":{"lng":10.211899,"lat":50.035101},"ril100":"NS"},"arrival":{"platform":"6","scheduledTime":"2023-10-18T16:56:00.000Z","time":"2023-10-18T16:56:00.000Z","reihung":false},"departure":{"platform":"6","scheduledTime":"2023-10-18T16:57:00.000Z","time":"2023-10-18T16:57:00.000Z","reihung":false}},{"station":{"evaNumber":"8000260","name":"Würzburg Hbf","coordinates":{"lng":9.93593,"lat":49.802163},"ril100":"NWH"},"arrival":{"platform":"10 D-F","scheduledTime":"2023-10-18T17:21:00.000Z","time":"2023-10-18T17:21:00.000Z","reihung":false}}],"finalDestination":"Würzburg Hbf","jid":"1|360552|0|80|18102023","messages":[{"type":"A","code":"FB","prio":260,"icoX":4,"txtN":"Fahrradmitnahme begrenzt möglich"},{"type":"A","code":"RC","prio":320,"icoX":2,"txtN":"Reservierung an DB-Automaten/Reisezentren/vielen DB-Agenturen möglich"},{"type":"A","code":"ER","prio":560,"icoX":2,"txtN":"Rampe im Zug"},{"type":"A","code":"LS","prio":605,"icoX":2,"txtN":"Laptop-Steckdosen"},{"type":"A","code":"KL","prio":610,"icoX":2,"txtN":"Klimaanlage"},{"type":"M","code":"","icoX":10,"txtS":"RE 4794: Bamberg->Würzburg Hbf: Bauarbeiten.","txtN":"Bauarbeiten zwischen Bamberg und Nürnberg Hbf in der Zeit vom 10. Dezember bis 16. Dezember 2023. Es kommt zu Fahrplanänderungen und Zugausfällen mit Schienenersatzverkehr. Wichtige Informationen finden Sie unter: https://t1p.de/px28w","url":"https://t1p.de/ftht0","sIdx":1}],"type":"JNY"}],"segmentTypes":["ICE","RE"]},{"checksum":"8e2ad9e2_3","cid":"C-3","date":"2023-10-17T22:00:00.000Z","duration":13440000,"changes":1,"isRideable":true,"arrival":{"platform":"6","scheduledTime":"2023-10-18T17:48:00.000Z","time":"2023-10-18T17:48:00.000Z","reihung":false},"departure":{"platform":"2","scheduledTime":"2023-10-18T14:04:00.000Z","time":"2023-10-18T14:04:00.000Z","reihung":false},"segments":[{"arrival":{"platform":"8","scheduledTime":"2023-10-18T16:56:00.000Z","time":"2023-10-18T16:56:00.000Z","reihung":false},"departure":{"platform":"2","scheduledTime":"2023-10-18T14:04:00.000Z","time":"2023-10-18T14:04:00.000Z","reihung":false},"duration":10320000,"train":{"name":"ICE 1007","line":"29","admin":"80","number":"1007","type":"ICE","operator":{"name":"DB Fernverkehr AG","icoX":1}},"changeDuration":5,"segmentStart":{"name":"Berlin Hbf (tief)","evaNumber":"8098160"},"segmentDestination":{"name":"Nürnberg Hbf","evaNumber":"8000284"},"stops":[{"station":{"evaNumber":"8098160","name":"Berlin Hbf (tief)","coordinates":{"lng":13.368892,"lat":52.52585},"ril100":"BL"},"departure":{"platform":"2","scheduledTime":"2023-10-18T14:04:00.000Z","time":"2023-10-18T14:04:00.000Z","reihung":false}},{"station":{"evaNumber":"8011113","name":"Berlin Südkreuz","coordinates":{"lng":13.365863,"lat":52.47623},"ril100":"BPAF"},"arrival":{"platform":"3","scheduledTime":"2023-10-18T14:09:00.000Z","time":"2023-10-18T14:09:00.000Z","reihung":false},"departure":{"platform":"3","scheduledTime":"2023-10-18T14:11:00.000Z","time":"2023-10-18T14:11:00.000Z","reihung":false},"auslastung":{"first":3,"second":2}},{"station":{"evaNumber":"8010159","name":"Halle(Saale)Hbf","coordinates":{"lng":11.98699,"lat":51.477079},"ril100":"LH"},"arrival":{"platform":"6","scheduledTime":"2023-10-18T15:16:00.000Z","time":"2023-10-18T15:16:00.000Z","reihung":false},"departure":{"platform":"6","scheduledTime":"2023-10-18T15:18:00.000Z","time":"2023-10-18T15:18:00.000Z","reihung":false},"auslastung":{"first":3,"second":2}},{"station":{"evaNumber":"8010101","name":"Erfurt Hbf","coordinates":{"lng":11.038502,"lat":50.97255},"ril100":"UE  P"},"arrival":{"platform":"1","scheduledTime":"2023-10-18T15:45:00.000Z","time":"2023-10-18T15:45:00.000Z","reihung":false},"departure":{"platform":"1","scheduledTime":"2023-10-18T15:47:00.000Z","time":"2023-10-18T15:47:00.000Z","reihung":false},"auslastung":{"first":3,"second":2}},{"station":{"evaNumber":"8000284","name":"Nürnberg Hbf","coordinates":{"lng":11.08227,"lat":49.445435},"ril100":"NN"},"arrival":{"platform":"8","scheduledTime":"2023-10-18T16:56:00.000Z","time":"2023-10-18T16:56:00.000Z","reihung":false}}],"finalDestination":"München Hbf","jid":"1|195221|0|80|18102023","auslastung":{"first":3,"second":2},"messages":[{"type":"A","code":"CK","prio":200,"icoX":2,"txtN":"Sicher & kontaktlos ohne Ticketkontrolle reisen mit Komfort Check-in"},{"type":"A","code":"BR","prio":450,"icoX":5,"txtN":"Bordrestaurant"},{"type":"A","code":"IT","prio":100,"icoX":16,"txtN":"ICE Sprinter"}],"type":"JNY"},{"arrival":{"platform":"6","scheduledTime":"2023-10-18T17:48:00.000Z","time":"2023-10-18T17:48:00.000Z","reihung":false},"departure":{"platform":"4","scheduledTime":"2023-10-18T17:01:00.000Z","time":"2023-10-18T17:01:00.000Z","reihung":false},"duration":2820000,"train":{"name":"ICE 526","line":"29","admin":"80","number":"526","type":"ICE","operator":{"name":"DB Fernverkehr AG","icoX":1}},"segmentStart":{"name":"Nürnberg Hbf","evaNumber":"8000284"},"segmentDestination":{"name":"Würzburg Hbf","evaNumber":"8000260"},"stops":[{"station":{"evaNumber":"8000284","name":"Nürnberg Hbf","coordinates":{"lng":11.08227,"lat":49.445435},"ril100":"NN"},"departure":{"platform":"4","scheduledTime":"2023-10-18T17:01:00.000Z","time":"2023-10-18T17:01:00.000Z","reihung":false},"auslastung":{"first":1,"second":1}},{"station":{"evaNumber":"8000260","name":"Würzburg Hbf","coordinates":{"lng":9.93593,"lat":49.802163},"ril100":"NWH"},"arrival":{"platform":"6","scheduledTime":"2023-10-18T17:48:00.000Z","time":"2023-10-18T17:48:00.000Z","reihung":false}}],"finalDestination":"Dortmund Hbf","jid":"1|205552|0|80|18102023","auslastung":{"first":1,"second":1},"messages":[{"type":"A","code":"CK","prio":200,"icoX":2,"txtN":"Sicher & kontaktlos ohne Ticketkontrolle reisen mit Komfort Check-in"}],"type":"JNY"}],"segmentTypes":["ICE","ICE"]},{"checksum":"7a35f345_3","cid":"C-4","date":"2023-10-17T22:00:00.000Z","duration":13920000,"changes":1,"isRideable":true,"arrival":{"platform":"11 D-F","scheduledTime":"2023-10-18T18:21:00.000Z","time":"2023-10-18T18:21:00.000Z","reihung":false},"departure":{"platform":"1","scheduledTime":"2023-10-18T14:29:00.000Z","time":"2023-10-18T14:29:00.000Z","reihung":false},"segments":[{"arrival":{"platform":"3","scheduledTime":"2023-10-18T17:14:00.000Z","time":"2023-10-18T17:14:00.000Z","reihung":false},"departure":{"platform":"1","scheduledTime":"2023-10-18T14:29:00.000Z","time":"2023-10-18T14:29:00.000Z","reihung":false},"duration":9900000,"train":{"name":"ICE 603","line":"28","admin":"80","number":"603","type":"ICE","operator":{"name":"DB Fernverkehr AG","icoX":1}},"changeDuration":12,"segmentStart":{"name":"Berlin Hbf (tief)","evaNumber":"8098160"},"segmentDestination":{"name":"Bamberg","evaNumber":"8000025"},"stops":[{"station":{"evaNumber":"8098160","name":"Berlin Hbf (tief)","coordinates":{"lng":13.368892,"lat":52.52585},"ril100":"BL"},"departure":{"platform":"1","scheduledTime":"2023-10-18T14:29:00.000Z","time":"2023-10-18T14:29:00.000Z","reihung":false}},{"station":{"evaNumber":"8011113","name":"Berlin Südkreuz","coordinates":{"lng":13.365863,"lat":52.47623},"ril100":"BPAF"},"arrival":{"platform":"3","scheduledTime":"2023-10-18T14:34:00.000Z","time":"2023-10-18T14:34:00.000Z","reihung":false},"departure":{"platform":"3","scheduledTime":"2023-10-18T14:36:00.000Z","time":"2023-10-18T14:36:00.000Z","reihung":false},"auslastung":{"first":2,"second":2}},{"station":{"evaNumber":"8010222","name":"Lutherstadt Wittenberg Hbf","coordinates":{"lng":12.661999,"lat":51.867579},"ril100":"LW"},"arrival":{"platform":"2","scheduledTime":"2023-10-18T15:10:00.000Z","time":"2023-10-18T15:10:00.000Z","reihung":false},"departure":{"platform":"2","scheduledTime":"2023-10-18T15:11:00.000Z","time":"2023-10-18T15:11:00.000Z","reihung":false},"auslastung":{"first":2,"second":2}},{"station":{"evaNumber":"8010205","name":"Leipzig Hbf","coordinates":{"lng":12.381167,"lat":51.345081},"ril100":"LL"},"arrival":{"platform":"13","scheduledTime":"2023-10-18T15:42:00.000Z","time":"2023-10-18T15:42:00.000Z","reihung":false},"departure":{"platform":"13","scheduledTime":"2023-10-18T15:48:00.000Z","time":"2023-10-18T15:48:00.000Z","reihung":false},"auslastung":{"first":1,"second":1}},{"station":{"evaNumber":"8010101","name":"Erfurt Hbf","coordinates":{"lng":11.038502,"lat":50.97255},"ril100":"UE  P"},"arrival":{"platform":"1","scheduledTime":"2023-10-18T16:29:00.000Z","time":"2023-10-18T16:29:00.000Z","reihung":false},"departure":{"platform":"1","scheduledTime":"2023-10-18T16:31:00.000Z","time":"2023-10-18T16:31:00.000Z","reihung":false},"auslastung":{"first":1,"second":1}},{"station":{"evaNumber":"8000025","name":"Bamberg","coordinates":{"lng":10.899493,"lat":49.900793},"ril100":"NBA"},"arrival":{"platform":"3","scheduledTime":"2023-10-18T17:14:00.000Z","time":"2023-10-18T17:14:00.000Z","reihung":false}}],"finalDestination":"München Hbf","jid":"1|207102|0|80|18102023","auslastung":{"first":2,"second":2},"messages":[{"type":"A","code":"CK","prio":200,"icoX":2,"txtN":"Sicher & kontaktlos ohne Ticketkontrolle reisen mit Komfort Check-in"},{"type":"A","code":"FR","prio":260,"icoX":3,"txtN":"Fahrradmitnahme reservierungspflichtig"},{"type":"A","code":"FB","prio":260,"icoX":4,"txtN":"Fahrradmitnahme begrenzt möglich"},{"type":"A","code":"BR","prio":450,"icoX":5,"txtN":"Bordrestaurant"},{"type":"A","code":"EH","prio":560,"icoX":2,"txtN":"Fahrzeuggebundene Einstiegshilfe vorhanden"}],"type":"JNY"},{"arrival":{"platform":"11 D-F","scheduledTime":"2023-10-18T18:21:00.000Z","time":"2023-10-18T18:21:00.000Z","reihung":false},"departure":{"platform":"2","scheduledTime":"2023-10-18T17:26:00.000Z","time":"2023-10-18T17:26:00.000Z","reihung":false},"duration":3300000,"train":{"name":"RE 54","line":"54","admin":"800772","number":"58584","type":"RE","operator":{"name":"DB Regio AG Bayern","icoX":7}},"segmentStart":{"name":"Bamberg","evaNumber":"8000025"},"segmentDestination":{"name":"Würzburg Hbf","evaNumber":"8000260"},"stops":[{"station":{"evaNumber":"8000025","name":"Bamberg","coordinates":{"lng":10.899493,"lat":49.900793},"ril100":"NBA"},"departure":{"platform":"2","scheduledTime":"2023-10-18T17:26:00.000Z","time":"2023-10-18T17:26:00.000Z","reihung":false}},{"station":{"evaNumber":"8002630","name":"Haßfurt","coordinates":{"lng":10.509765,"lat":50.033366},"ril100":"NHT"},"arrival":{"platform":"2","scheduledTime":"2023-10-18T17:41:00.000Z","time":"2023-10-18T17:41:00.000Z","reihung":false},"departure":{"platform":"2","scheduledTime":"2023-10-18T17:42:00.000Z","time":"2023-10-18T17:42:00.000Z","reihung":false}},{"station":{"evaNumber":"8000032","name":"Schweinfurt Hbf","coordinates":{"lng":10.211899,"lat":50.035101},"ril100":"NS"},"arrival":{"platform":"6","scheduledTime":"2023-10-18T17:55:00.000Z","time":"2023-10-18T17:55:00.000Z","reihung":false},"departure":{"platform":"6","scheduledTime":"2023-10-18T17:56:00.000Z","time":"2023-10-18T17:56:00.000Z","reihung":false}},{"station":{"evaNumber":"8000260","name":"Würzburg Hbf","coordinates":{"lng":9.93593,"lat":49.802163},"ril100":"NWH"},"arrival":{"platform":"11 D-F","scheduledTime":"2023-10-18T18:21:00.000Z","time":"2023-10-18T18:21:00.000Z","reihung":false}}],"finalDestination":"Würzburg Hbf","jid":"1|269887|1|80|18102023","messages":[{"type":"A","code":"FB","prio":260,"icoX":4,"txtN":"Fahrradmitnahme begrenzt möglich"},{"type":"A","code":"RC","prio":320,"icoX":2,"txtN":"Reservierung an DB-Automaten/Reisezentren/vielen DB-Agenturen möglich"},{"type":"A","code":"EH","prio":560,"icoX":2,"txtN":"Fahrzeuggebundene Einstiegshilfe vorhanden"},{"type":"A","code":"KL","prio":610,"icoX":2,"txtN":"Klimaanlage"},{"type":"A","code":"KI","prio":610,"icoX":2,"txtN":"Kinderspielecke"},{"type":"M","code":"","icoX":10,"txtS":"RE 58584: Bamberg->Würzburg Hbf: Störung.","txtN":"Auf Grund von kurzfristiger Personalengpässen beim Infrastrukturbetreiber kommt es zu Verspätungen und Haltausfällen wegen Umleitungen mit Fahrtrichtungswechsel an einigen Nächten von 06.10.23 bis 25.10.23 jeweils von 18:00 Uhr bis 06:00 Uhr bzw. von 20:00 Uhr bis 06:00 Uhr zw. Aschaffenburg Hbf und Hanau Hbf, sowie im weiteren Fahrtverlauf. Bei einigen Zügen ist der Zusatzhalt Großkrotzenburg eingeplant. Bitte beachten Sie dies bei der Reiseplanung.","sIdx":1}],"type":"JNY"}],"segmentTypes":["ICE","RE"]},{"checksum":"961b1517_3","cid":"C-5","date":"2023-10-17T22:00:00.000Z","duration":13620000,"changes":1,"isRideable":true,"arrival":{"platform":"10 D-F","scheduledTime":"2023-10-18T19:21:00.000Z","time":"2023-10-18T19:21:00.000Z","reihung":false},"departure":{"platform":"1","scheduledTime":"2023-10-18T15:34:00.000Z","time":"2023-10-18T15:34:00.000Z","reihung":false},"segments":[{"arrival":{"platform":"3","scheduledTime":"2023-10-18T18:15:00.000Z","time":"2023-10-18T18:15:00.000Z","reihung":false},"departure":{"platform":"1","scheduledTime":"2023-10-18T15:34:00.000Z","time":"2023-10-18T15:34:00.000Z","reihung":false},"duration":9660000,"train":{"name":"ICE 801","line":"18","admin":"80","number":"801","type":"ICE","operator":{"name":"DB Fernverkehr AG","icoX":1}},"changeDuration":12,"segmentStart":{"name":"Berlin Hbf (tief)","evaNumber":"8098160"},"segmentDestination":{"name":"Bamberg","evaNumber":"8000025"},"stops":[{"station":{"evaNumber":"8098160","name":"Berlin Hbf (tief)","coordinates":{"lng":13.368892,"lat":52.52585},"ril100":"BL"},"departure":{"platform":"1","scheduledTime":"2023-10-18T15:34:00.000Z","time":"2023-10-18T15:34:00.000Z","reihung":false}},{"station":{"evaNumber":"8011113","name":"Berlin Südkreuz","coordinates":{"lng":13.365863,"lat":52.47623},"ril100":"BPAF"},"arrival":{"platform":"3","scheduledTime":"2023-10-18T15:39:00.000Z","time":"2023-10-18T15:39:00.000Z","reihung":false},"departure":{"platform":"3","scheduledTime":"2023-10-18T15:41:00.000Z","time":"2023-10-18T15:41:00.000Z","reihung":false},"auslastung":{"first":1,"second":1}},{"station":{"evaNumber":"8010050","name":"Bitterfeld","coordinates":{"lng":12.316966,"lat":51.622911},"ril100":"LBT"},"arrival":{"platform":"3","scheduledTime":"2023-10-18T16:32:00.000Z","time":"2023-10-18T16:32:00.000Z","reihung":false},"departure":{"platform":"3","scheduledTime":"2023-10-18T16:33:00.000Z","time":"2023-10-18T16:33:00.000Z","reihung":false},"auslastung":{"first":1,"second":1}},{"station":{"evaNumber":"8010159","name":"Halle(Saale)Hbf","coordinates":{"lng":11.98699,"lat":51.477079},"ril100":"LH"},"arrival":{"platform":"8","scheduledTime":"2023-10-18T16:50:00.000Z","time":"2023-10-18T16:50:00.000Z","reihung":false},"departure":{"platform":"8","scheduledTime":"2023-10-18T16:52:00.000Z","time":"2023-10-18T16:52:00.000Z","reihung":false},"auslastung":{"first":1,"second":1}},{"station":{"evaNumber":"8010101","name":"Erfurt Hbf","coordinates":{"lng":11.038502,"lat":50.97255},"ril100":"UE  P"},"arrival":{"platform":"1","scheduledTime":"2023-10-18T17:24:00.000Z","time":"2023-10-18T17:24:00.000Z","reihung":false},"departure":{"platform":"1","scheduledTime":"2023-10-18T17:32:00.000Z","time":"2023-10-18T17:32:00.000Z","reihung":false},"auslastung":{"first":1,"second":1}},{"station":{"evaNumber":"8000025","name":"Bamberg","coordinates":{"lng":10.899493,"lat":49.900793},"ril100":"NBA"},"arrival":{"platform":"3","scheduledTime":"2023-10-18T18:15:00.000Z","time":"2023-10-18T18:15:00.000Z","reihung":false}}],"finalDestination":"München Hbf","jid":"1|210399|0|80|18102023","auslastung":{"first":1,"second":1},"messages":[{"type":"A","code":"CK","prio":200,"icoX":2,"txtN":"Sicher & kontaktlos ohne Ticketkontrolle reisen mit Komfort Check-in"},{"type":"A","code":"FR","prio":260,"icoX":3,"txtN":"Fahrradmitnahme reservierungspflichtig"},{"type":"A","code":"FB","prio":260,"icoX":4,"txtN":"Fahrradmitnahme begrenzt möglich"},{"type":"A","code":"BR","prio":450,"icoX":5,"txtN":"Bordrestaurant"},{"type":"A","code":"EH","prio":560,"icoX":2,"txtN":"Fahrzeuggebundene Einstiegshilfe vorhanden"}],"type":"JNY"},{"arrival":{"platform":"10 D-F","scheduledTime":"2023-10-18T19:21:00.000Z","time":"2023-10-18T19:21:00.000Z","reihung":false},"departure":{"platform":"6","scheduledTime":"2023-10-18T18:27:00.000Z","time":"2023-10-18T18:27:00.000Z","reihung":false},"duration":3240000,"train":{"name":"RE 20","line":"20","admin":"800755","number":"4796","type":"RE","operator":{"name":"DB Regio AG Bayern","icoX":7}},"segmentStart":{"name":"Bamberg","evaNumber":"8000025"},"segmentDestination":{"name":"Würzburg Hbf","evaNumber":"8000260"},"stops":[{"station":{"evaNumber":"8000025","name":"Bamberg","coordinates":{"lng":10.899493,"lat":49.900793},"ril100":"NBA"},"departure":{"platform":"6","scheduledTime":"2023-10-18T18:27:00.000Z","time":"2023-10-18T18:27:00.000Z","reihung":false}},{"station":{"evaNumber":"8002630","name":"Haßfurt","coordinates":{"lng":10.509765,"lat":50.033366},"ril100":"NHT"},"arrival":{"platform":"2","scheduledTime":"2023-10-18T18:42:00.000Z","time":"2023-10-18T18:42:00.000Z","reihung":false},"departure":{"platform":"2","scheduledTime":"2023-10-18T18:43:00.000Z","time":"2023-10-18T18:43:00.000Z","reihung":false}},{"station":{"evaNumber":"8000032","name":"Schweinfurt Hbf","coordinates":{"lng":10.211899,"lat":50.035101},"ril100":"NS"},"arrival":{"platform":"6","scheduledTime":"2023-10-18T18:55:00.000Z","time":"2023-10-18T18:55:00.000Z","reihung":false},"departure":{"platform":"6","scheduledTime":"2023-10-18T18:56:00.000Z","time":"2023-10-18T18:56:00.000Z","reihung":false}},{"station":{"evaNumber":"8000260","name":"Würzburg Hbf","coordinates":{"lng":9.93593,"lat":49.802163},"ril100":"NWH"},"arrival":{"platform":"10 D-F","scheduledTime":"2023-10-18T19:21:00.000Z","time":"2023-10-18T19:21:00.000Z","reihung":false}}],"finalDestination":"Würzburg Hbf","jid":"1|360558|0|80|18102023","messages":[{"type":"A","code":"FB","prio":260,"icoX":4,"txtN":"Fahrradmitnahme begrenzt möglich"},{"type":"A","code":"RC","prio":320,"icoX":2,"txtN":"Reservierung an DB-Automaten/Reisezentren/vielen DB-Agenturen möglich"},{"type":"A","code":"ER","prio":560,"icoX":2,"txtN":"Rampe im Zug"},{"type":"A","code":"LS","prio":605,"icoX":2,"txtN":"Laptop-Steckdosen"},{"type":"A","code":"KL","prio":610,"icoX":2,"txtN":"Klimaanlage"},{"type":"M","code":"","icoX":10,"txtS":"RE 4796: Bamberg->Würzburg Hbf: Bauarbeiten.","txtN":"Bauarbeiten zwischen Bamberg und Nürnberg Hbf in der Zeit vom 10. Dezember bis 16. Dezember 2023. Es kommt zu Fahrplanänderungen und Zugausfällen mit Schienenersatzverkehr. Wichtige Informationen finden Sie unter: https://t1p.de/px28w","url":"https://t1p.de/ftht0","sIdx":1}],"type":"JNY"}],"segmentTypes":["ICE","RE"]}]}